{
  "mappings" : {
    "_source" : {
      "excludes" : [
        "content_ar",
        "content_bg",
        "content_bn",
        "content_ca",
        "content_ckb-iq",
        "content_cs",
        "content_da",
        "content_de",
        "content_el",
        "content_en",
        "content_en-ie",
        "content_es",
        "content_et",
        "content_eu",
        "content_fa",
        "content_fi",
        "content_fr",
        "content_gl",
        "content_gu",
        "content_he",
        "content_hi",
        "content_hr",
        "content_hu",
        "content_hy",
        "content_id",
        "content_it",
        "content_ja",
        "content_ko",
        "content_lt",
        "content_lv",
        "content_mk",
        "content_ml",
        "content_nl",
        "content_no",
        "content_pa",
        "content_pl",
        "content_pt",
        "content_pt-br",
        "content_ro",
        "content_ru",
        "content_si",
        "content_sq",
        "content_sv",
        "content_ta",
        "content_te",
        "content_th",
        "content_tl",
        "content_tr",
        "content_uk",
        "content_ur",
        "content_vi",
        "content_zh-cn",
        "content_zh-tw",
        "important_content_ar",
        "important_content_bg",
        "important_content_bn",
        "important_content_ca",
        "important_content_ckb-iq",
        "important_content_cs",
        "important_content_da",
        "important_content_de",
        "important_content_el",
        "important_content_en",
        "important_content_en-ie",
        "important_content_es",
        "important_content_et",
        "important_content_eu",
        "important_content_fa",
        "important_content_fi",
        "important_content_fr",
        "important_content_gl",
        "important_content_gu",
        "important_content_he",
        "important_content_hi",
        "important_content_hr",
        "important_content_hu",
        "important_content_hy",
        "important_content_id",
        "important_content_it",
        "important_content_ja",
        "important_content_ko",
        "important_content_lt",
        "important_content_lv",
        "important_content_mk",
        "important_content_ml",
        "important_content_nl",
        "important_content_no",
        "important_content_pa",
        "important_content_pl",
        "important_content_pt",
        "important_content_pt-br",
        "important_content_ro",
        "important_content_ru",
        "important_content_si",
        "important_content_sq",
        "important_content_sv",
        "important_content_ta",
        "important_content_te",
        "important_content_th",
        "important_content_tl",
        "important_content_tr",
        "important_content_uk",
        "important_content_ur",
        "important_content_vi",
        "important_content_zh-cn",
        "important_content_zh-tw",
        "title_ar",
        "title_bg",
        "title_bn",
        "title_ca",
        "title_ckb-iq",
        "title_cs",
        "title_da",
        "title_de",
        "title_el",
        "title_en",
        "title_en-ie",
        "title_es",
        "title_et",
        "title_eu",
        "title_fa",
        "title_fi",
        "title_fr",
        "title_gl",
        "title_gu",
        "title_he",
        "title_hi",
        "title_hr",
        "title_hu",
        "title_hy",
        "title_id",
        "title_it",
        "title_ja",
        "title_ko",
        "title_lt",
        "title_lv",
        "title_mk",
        "title_ml",
        "title_nl",
        "title_no",
        "title_pa",
        "title_pl",
        "title_pt",
        "title_pt-br",
        "title_ro",
        "title_ru",
        "title_si",
        "title_sq",
        "title_sv",
        "title_ta",
        "title_te",
        "title_th",
        "title_tl",
        "title_tr",
        "title_uk",
        "title_ur",
        "title_vi",
        "title_zh-cn",
        "title_zh-tw"
      ]
    },
    "dynamic_templates" : [
      {
        "lang_en" : {
          "match" : "*_en",
          "mapping" : {
            "analyzer" : "english_analyzer",
            "type" : "text"
          }
        }
      }
    ],
    "properties" : {
      "anchor" : {
        "type" : "keyword"
      },
      "boost" : {
        "type" : "float"
      },
      "click_count" : {
        "type" : "long"
      },
      "config_id" : {
        "type" : "keyword"
      },
      "text_vector": {
        "type": "dense_vector",
        "dims": 384,
        "index": true,
        "similarity": "cosine"
      },
      "hudx_keywords_new": {
        "type": "text",
        "fielddata": true
      },
      "hudx_digest_new": {
        "type": "text",
        "fielddata": true
      },
      "content" : {
        "type" : "text",
        "copy_to" : [
          "content_no_stem",
          "suggest_terms",
          "suggest_trigrams"
        ],
        "term_vector" : "with_positions_offsets",
        "analyzer" : "standard_analyzer",
        "search_analyzer" : "standard_search_analyzer"
      },
      "content_ar" : {
        "type" : "text",
        "fields" : {
          "keyword" : {
            "type" : "keyword",
            "ignore_above" : 256
          }
        }
      },
      "content_de" : {
        "type" : "text",
        "fields" : {
          "keyword" : {
            "type" : "keyword",
            "ignore_above" : 256
          }
        }
      },
      "content_el" : {
        "type" : "text",
        "fields" : {
          "keyword" : {
            "type" : "keyword",
            "ignore_above" : 256
          }
        }
      },
      "content_en" : {
        "type" : "text",
        "analyzer" : "english_analyzer"
      },
      "content_es" : {
        "type" : "text",
        "fields" : {
          "keyword" : {
            "type" : "keyword",
            "ignore_above" : 256
          }
        }
      },
      "content_fa" : {
        "type" : "text",
        "fields" : {
          "keyword" : {
            "type" : "keyword",
            "ignore_above" : 256
          }
        }
      },
      "content_fr" : {
        "type" : "text",
        "fields" : {
          "keyword" : {
            "type" : "keyword",
            "ignore_above" : 256
          }
        }
      },
      "content_it" : {
        "type" : "text",
        "fields" : {
          "keyword" : {
            "type" : "keyword",
            "ignore_above" : 256
          }
        }
      },
      "content_ko" : {
        "type" : "text",
        "fields" : {
          "keyword" : {
            "type" : "keyword",
            "ignore_above" : 256
          }
        }
      },
      "content_length" : {
        "type" : "long"
      },
      "content_minhash_bits" : {
        "type" : "keyword"
      },
      "content_nl" : {
        "type" : "text",
        "fields" : {
          "keyword" : {
            "type" : "keyword",
            "ignore_above" : 256
          }
        }
      },
      "content_no_stem" : {
        "type" : "text",
        "term_vector" : "with_positions_offsets",
        "analyzer" : "standard_analyzer_no_stem"
      },
      "content_pt" : {
        "type" : "text",
        "fields" : {
          "keyword" : {
            "type" : "keyword",
            "ignore_above" : 256
          }
        }
      },
      "content_ru" : {
        "type" : "text",
        "fields" : {
          "keyword" : {
            "type" : "keyword",
            "ignore_above" : 256
          }
        }
      },
      "content_sv" : {
        "type" : "text",
        "fields" : {
          "keyword" : {
            "type" : "keyword",
            "ignore_above" : 256
          }
        }
      },
      "content_tl" : {
        "type" : "text",
        "fields" : {
          "keyword" : {
            "type" : "keyword",
            "ignore_above" : 256
          }
        }
      },
      "content_vi" : {
        "type" : "text",
        "fields" : {
          "keyword" : {
            "type" : "keyword",
            "ignore_above" : 256
          }
        }
      },
      "created" : {
        "type" : "date",
        "format" : "date_optional_time"
      },
      "digest" : {
        "type" : "text",
        "index" : false
      },
      "doc_id" : {
        "type" : "keyword"
      },
      "expires" : {
        "type" : "date",
        "format" : "date_optional_time"
      },
      "favorite_count" : {
        "type" : "long"
      },
      "filename" : {
        "type" : "keyword"
      },
      "filetype" : {
        "type" : "keyword"
      },
      "host" : {
        "type" : "keyword"
      },
      "hudx_ccf" : {
        "type" : "flattened"
      },
      "hudx_ccr" : {
        "type" : "keyword",
        "index" : false
      },
      "hudx_cd" : {
        "type" : "date",
        "format" : "date_optional_time"
      },
      "hudx_cl" : {
        "type" : "keyword"
      },
      "hudx_cs" : {
        "type" : "keyword"
      },
      "hudx_ct" : {
        "type" : "keyword"
      },
      "hudx_dc" : {
        "type" : "date",
        "format" : "date_optional_time"
      },
      "hudx_dm" : {
        "type" : "date",
        "format" : "date_optional_time"
      },
      "hudx_dp" : {
        "type" : "date",
        "format" : "date_optional_time"
      },
      "hudx_dr" : {
        "type" : "date",
        "format" : "date_optional_time",
        "null_value" : "2010-01-01T00:00:00"
      },
      "hudx_dsp" : {
        "type" : "text",
        "analyzer" : "pipe_splitter",
        "fielddata" : true
      },
      "hudx_pop" : {
        "type" : "float"
      },
      "important_content" : {
        "type" : "text",
        "analyzer" : "standard_analyzer",
        "search_analyzer" : "standard_search_analyzer"
      },
      "important_content_en" : {
        "type" : "text",
        "analyzer" : "english_analyzer"
      },
      "label" : {
        "type" : "keyword"
      },
      "lang" : {
        "type" : "keyword"
      },
      "last_modified" : {
        "type" : "date",
        "format" : "date_optional_time"
      },
      "location" : {
        "type" : "geo_point"
      },
      "mimetype" : {
        "type" : "keyword"
      },
      "paragraph_content" : {
        "type" : "text",
        "term_vector" : "with_positions_offsets",
        "analyzer" : "standard_analyzer_no_stem"
      },
      "parent_id" : {
        "type" : "keyword"
      },
      "role" : {
        "type" : "keyword"
      },
      "segment" : {
        "type" : "keyword"
      },
      "site" : {
        "type" : "keyword"
      },
      "suggest_terms" : {
        "type" : "text",
        "analyzer" : "suggester_search_analyzer"
      },
      "suggest_trigrams" : {
        "type" : "text",
        "analyzer" : "trigram"
      },
      "thumbnail" : {
        "type" : "keyword"
      },
      "timestamp" : {
        "type" : "date",
        "format" : "date_optional_time"
      },
      "title" : {
        "type" : "text",
        "copy_to" : [
          "suggest_terms",
          "suggest_trigrams"
        ],
        "term_vector" : "with_positions_offsets",
        "analyzer" : "standard_analyzer",
        "search_analyzer" : "standard_search_analyzer"
      },
      "title_ar" : {
        "type" : "text",
        "fields" : {
          "keyword" : {
            "type" : "keyword",
            "ignore_above" : 256
          }
        }
      },
      "title_de" : {
        "type" : "text",
        "fields" : {
          "keyword" : {
            "type" : "keyword",
            "ignore_above" : 256
          }
        }
      },
      "title_el" : {
        "type" : "text",
        "fields" : {
          "keyword" : {
            "type" : "keyword",
            "ignore_above" : 256
          }
        }
      },
      "title_en" : {
        "type" : "text",
        "analyzer" : "english_analyzer"
      },
      "title_es" : {
        "type" : "text",
        "fields" : {
          "keyword" : {
            "type" : "keyword",
            "ignore_above" : 256
          }
        }
      },
      "title_fa" : {
        "type" : "text",
        "fields" : {
          "keyword" : {
            "type" : "keyword",
            "ignore_above" : 256
          }
        }
      },
      "title_fr" : {
        "type" : "text",
        "fields" : {
          "keyword" : {
            "type" : "keyword",
            "ignore_above" : 256
          }
        }
      },
      "title_it" : {
        "type" : "text",
        "fields" : {
          "keyword" : {
            "type" : "keyword",
            "ignore_above" : 256
          }
        }
      },
      "title_ko" : {
        "type" : "text",
        "fields" : {
          "keyword" : {
            "type" : "keyword",
            "ignore_above" : 256
          }
        }
      },
      "title_nl" : {
        "type" : "text",
        "fields" : {
          "keyword" : {
            "type" : "keyword",
            "ignore_above" : 256
          }
        }
      },
      "title_pt" : {
        "type" : "text",
        "fields" : {
          "keyword" : {
            "type" : "keyword",
            "ignore_above" : 256
          }
        }
      },
      "title_ru" : {
        "type" : "text",
        "fields" : {
          "keyword" : {
            "type" : "keyword",
            "ignore_above" : 256
          }
        }
      },
      "title_sv" : {
        "type" : "text",
        "fields" : {
          "keyword" : {
            "type" : "keyword",
            "ignore_above" : 256
          }
        }
      },
      "title_tl" : {
        "type" : "text",
        "fields" : {
          "keyword" : {
            "type" : "keyword",
            "ignore_above" : 256
          }
        }
      },
      "title_vi" : {
        "type" : "text",
        "fields" : {
          "keyword" : {
            "type" : "keyword",
            "ignore_above" : 256
          }
        }
      },
      "url" : {
        "type" : "keyword"
      },
      "virtual_host" : {
        "type" : "keyword"
      }
    }
  },
  "settings" : {
    "analysis" : {
      "filter" : {
        "english_keywords" : {
          "type" : "keyword_marker",
          "keywords_path" : "dictionary/en/protwords.txt"
        },
        "hudx_override" : {
          "type" : "stemmer_override",
          "rules_path" : "dictionary/hudx/stemmer_override.txt"
        },
        "hudx_synonym_filter" : {
          "type" : "synonym_graph",
          "synonyms_path" : "dictionary/hudx/synonyms.txt",
          "updateable" : "true"
        },
        "stopword_en_filter" : {
          "type" : "stop",
          "stopwords_path" : "dictionary/en/stopwords.txt"
        },
        "hudx_keywords" : {
          "type" : "keyword_marker",
          "keywords_path" : "dictionary/hudx/protwords.txt"
        },
        "synonym_filter" : {
          "type" : "synonym_graph",
          "synonyms_path" : "dictionary/synonym.txt"
        },
        "truncate10_filter" : {
          "length" : "10",
          "type" : "truncate"
        },
        "truncate20_filter" : {
          "length" : "20",
          "type" : "truncate"
        },
        "english_override" : {
          "type" : "stemmer_override",
          "rules_path" : "dictionary/en/stemmer_override.txt"
        },
        "minhash_filter" : {
          "bit" : "2",
          "seed" : "1",
          "size" : "64",
          "type" : "min_hash"
        },
        "shingle" : {
          "max_shingle_size" : "3",
          "min_shingle_size" : "2",
          "type" : "shingle"
        },
        "stemmer_en_filter" : {
          "name" : "english",
          "type" : "stemmer"
        },
        "possessive_stemmer_en_filter" : {
          "name" : "possessive_english",
          "type" : "stemmer"
        }
      },
      "char_filter" : {
        "mapping_ja_filter" : {
          "type" : "mapping",
          "mappings_path" : "dictionary/ja/mapping.txt"
        },
        "removeall_filter" : {
          "pattern" : "(.*)",
          "type" : "pattern_replace",
          "replacement" : ""
        },
        "mapping_filter" : {
          "type" : "mapping",
          "mappings_path" : "dictionary/mapping.txt"
        },
        "zero_width_spaces" : {
          "type" : "mapping",
          "mappings" : [
            "\\u200C=> "
          ]
        }
      },
      "analyzer" : {
        "suggester_search_analyzer" : {
          "filter" : [
            "lowercase",
            "english_keywords",
            "english_override",
            "possessive_stemmer_en_filter"
          ],
          "char_filter" : [
            "mapping_filter"
          ],
          "type" : "custom",
          "tokenizer" : "standard"
        },
        "standard_search_analyzer" : {
          "filter" : [
            "cjk_bigram",
            "lowercase",
            "stopword_en_filter",
            "english_keywords",
            "english_override",
            "stemmer_en_filter"
          ],
          "char_filter" : [
            "mapping_filter"
          ],
          "type" : "custom",
          "tokenizer" : "unigram_search_tokenizer"
        },
        "trigram" : {
          "filter" : [
            "lowercase",
            "shingle"
          ],
          "type" : "custom",
          "tokenizer" : "standard"
        },
        "analyzer_case_insensitive" : {
          "filter" : "lowercase",
          "type" : "custom",
          "tokenizer" : "keyword"
        },
        "empty_analyzer" : {
          "type" : "custom",
          "char_filter" : [
            "removeall_filter"
          ],
          "tokenizer" : "standard"
        },
        "synonym_search_analyzer" : {
          "filter" : [
            "cjk_bigram",
            "lowercase",
            "hudx_synonym_filter",
            "stopword_en_filter",
            "english_keywords",
            "english_override",
            "stemmer_en_filter"
          ],
          "char_filter" : [
            "mapping_filter"
          ],
          "type" : "custom",
          "tokenizer" : "unigram_search_tokenizer"
        },
        "standard_analyzer" : {
          "filter" : [
            "cjk_bigram",
            "lowercase",
            "asciifolding",
            "stopword_en_filter",
            "english_keywords",
            "english_override",
            "stemmer_en_filter"
          ],
          "char_filter" : [
            "mapping_filter"
          ],
          "type" : "custom",
          "tokenizer" : "unigram_tokenizer"
        },
        "reverse" : {
          "filter" : [
            "lowercase",
            "reverse"
          ],
          "type" : "custom",
          "tokenizer" : "standard"
        },
        "standard_analyzer_no_stem" : {
          "filter" : [
            "lowercase",
            "asciifolding"
          ],
          "char_filter" : [
            "mapping_filter"
          ],
          "type" : "custom",
          "tokenizer" : "standard"
        },
        "minhash_analyzer" : {
          "filter" : [
            "cjk_bigram",
            "lowercase",
            "stopword_en_filter",
            "english_keywords",
            "english_override",
            "stemmer_en_filter",
            "minhash_filter"
          ],
          "char_filter" : [
            "mapping_ja_filter"
          ],
          "type" : "custom",
          "tokenizer" : "unigram_search_tokenizer"
        },
        "english_analyzer" : {
          "filter" : [
            "truncate20_filter",
            "lowercase",
            "english_keywords",
            "english_override",
            "possessive_stemmer_en_filter"
          ],
          "type" : "custom",
          "tokenizer" : "standard"
        },
        "pipe_splitter" : {
          "type" : "custom",
          "tokenizer" : "split_on_pipe"
        }
      },
      "tokenizer" : {
        "split_on_pipe" : {
          "pattern" : "|",
          "type" : "pattern"
        },
        "unigram_search_tokenizer" : {
          "dynamic_reload" : "true",
          "expand" : "false",
          "reload_interval" : "1m",
          "type" : "ngram",
          "synonyms_path" : "dictionary/synonym.txt",
          "n" : "1"
        },
        "unigram_tokenizer" : {
          "dynamic_reload" : "true",
          "expand" : "true",
          "reload_interval" : "1m",
          "type" : "ngram",
          "synonyms_path" : "dictionary/synonym.txt",
          "n" : "1"
        },
        "bigram_tokenizer" : {
          "expand" : "false",
          "expand_ngram" : "true",
          "synonyms_path" : "dictionary/synonym.txt",
          "dynamic_reload" : "true",
          "reload_interval" : "1m",
          "type" : "ngram",
          "n" : "2"
        }
      }
    }
  }
}